README.rst
setup.py
radiotool/__init__.py
radiotool/utils.py
radiotool.egg-info/PKG-INFO
radiotool.egg-info/SOURCES.txt
radiotool.egg-info/dependency_links.txt
radiotool.egg-info/requires.txt
radiotool.egg-info/top_level.txt
radiotool/algorithms/__init__.py
radiotool/algorithms/build_table_full_backtrace.c
radiotool/algorithms/build_table_mem_efficient.c
radiotool/algorithms/build_table_mem_efficient_reference.py
radiotool/algorithms/constraints.py
radiotool/algorithms/librosa_analysis.py
radiotool/algorithms/novelty.py
radiotool/algorithms/retarget.py
radiotool/composer/__init__.py
radiotool/composer/composition.py
radiotool/composer/dynamic.py
radiotool/composer/effect.py
radiotool/composer/fade.py
radiotool/composer/label.py
radiotool/composer/rawtrack.py
radiotool/composer/rawvolume.py
radiotool/composer/segment.py
radiotool/composer/song.py
radiotool/composer/speech.py
radiotool/composer/timestretchsegment.py
radiotool/composer/track.py
radiotool/composer/volume.py
radiotool/composer/volumebreakpoint.py