Metadata-Version: 1.0
Name: radiotool
Version: 0.4.1
Summary: Tools for constructing and retargeting audio
Home-page: https://github.com/ucbvislab/radiotool
Author: Steve Rubin
Author-email: srubin@cs.berkeley.edu
License: ISC
Platform: UNKNOWN
